{
  "Authorization form": "Authorization form",
  "Enter password": "Enter password",
  "Enter usename": "Enter usename",
  "Log in": "Log in",
  "Log out": "Log out",
  "You entered an incorrect login or password": "You entered an incorrect login or password",
  "decrement": "decrement",
  "increment": "increment",
  "throw an error": "throw an error",
  "Войти": "Войти",
  "Главная": "Главная",
  "О сайте": "О сайте",
  "Обновить страницу": "Обновить страницу",
  "Произошла непредвиденная ошибка": "Произошла непредвиденная ошибка",
  "Страница не найдена": "Страница не найдена",
  "Язык": "Язык",
  "переключить": "переключить"
}
